message_printer/__init__.py
message_printer/message_printer.py
message_printer-0.0.3.dist-info/METADATA
message_printer-0.0.3.dist-info/WHEEL
message_printer-0.0.3.dist-info/RECORD
